{
  "RELEASE":{
  "ExpireDate":{"year":2030,"day":8,"month":5},
  "Rewards":{
    "Gems":750,
    "Coins":1500,
    "Potions":{"UltraLucky"}
  },
{
  "MINIONS":{
  "ExpireDate":{"year":2030,"day":8,"month":5},
  "Rewards":{
    "Gems":1000,
    "Potions":{"UltraLucky"}
  },
{
  "TUNGTUNGTUNG":{
  "ExpireDate":{"year":2030,"day":8,"month":5},
  "Rewards":{
    "Coins":2000,
    "Potions":{"Businessman"}
  },
{
  "FREEBIES":{
  "ExpireDate":{"year":2030,"day":8,"month":5},
  "Rewards":{
    "Gems":1250,
    "Coins":2500,
    "Potions":{"UltraLucky", "CRISIS"}
  },
{
  "ZAPNZING":{
  "ExpireDate":{"year":2030,"day":8,"month":5},
  "Rewards":{
    "Gems":1500,
    "Coins":3000,
    "Potions": {"CRISIS", "CRISIS", "CRISIS"}
  },
}
